package/__init__.py
package/square.py
squarefortest-0.1.0.dist-info/LICENSE
squarefortest-0.1.0.dist-info/METADATA
squarefortest-0.1.0.dist-info/WHEEL
squarefortest-0.1.0.dist-info/top_level.txt
squarefortest-0.1.0.dist-info/RECORD
