Metadata-Version: 2.1
Name: squarefortest
Version: 0.1.0
Summary: squaring input number
Home-page: https://github.com/LiChingai/squarefortest
Author: Li
Author-email: your.email@example.com
License: UNKNOWN
Platform: UNKNOWN
Classifier: Programming Language :: Python :: 3
Classifier: License :: OSI Approved :: MIT License
Classifier: Operating System :: OS Independent
Requires-Python: >=3.6
